Metadata-Version: 2.1
Name: airflow-provider-sample
Version: 0.0.1
Summary: A sample provider package built by Astronomer.
Home-page: http://astronomer.io/
Author: Pete DeJoy
Author-email: pete@astronomer.io
License: Apache License 2.0
Platform: UNKNOWN
Requires-Python: >=3.6
